SIM/pll_sys_sim.v
// =============================================================================
// JATI - Model perilaku PLL untuk SIMULASI SAJA
// Modul   : pll_sys (nama sama dengan IP PLL yang dibuat di Quartus)
//
// PENTING: File ini hanya untuk ModelSim/Icarus. JANGAN dimasukkan ke proyek
// Quartus, karena Quartus memakai pll_sys hasil IP Catalog. Kalau keduanya
// masuk, akan terjadi error "module pll_sys sudah didefinisikan".
//
// Perilaku yang dimodelkan:
//   - Selama rst = 1          : locked = 0, outclk_0 diam di 0
//   - Setelah rst dilepas     : locked = 1 setelah LOCK_CYCLES siklus refclk
//   - Setelah locked          : outclk_0 = refclk (50 MHz -> 50 MHz)
// =============================================================================
`timescale 1ns/1ps

module pll_sys #(
    parameter integer LOCK_CYCLES = 20
)(
    input  wire refclk,
    input  wire rst,
    output wire outclk_0,
    output reg  locked
);

    integer cnt;

    initial begin
        locked = 1'b0;
        cnt    = 0;
    end

    // Diperbarui di tepi turun agar outclk_0 mulai bersih di tepi naik berikutnya
    always @(negedge refclk or posedge rst) begin
        if (rst) begin
            cnt    <= 0;
            locked <= 1'b0;
        end else if (cnt < LOCK_CYCLES) begin
            cnt    <= cnt + 1;
        end else begin
            locked <= 1'b1;
        end
    end

    assign outclk_0 = locked ? refclk : 1'b0;

endmodule

RTL/clk_rst.v
// =============================================================================
// JATI - Secure Element e-Paspor
// Modul   : clk_rst
// Fungsi  : Membangkitkan clock sistem (lewat PLL) dan reset global yang aman.
//
// Alur:
//   clk_50 --> [PLL pll_sys] --> clk_pll  (ke glitch_inj, lalu menjadi clk_sys)
//   rst_n  --+--> reset PLL
//            +--> [gabung dengan pll_locked] --> [sinkronizer 3 FF]
//                 --> [penahan reset HOLD_CYCLES] --> rst_sync_n
//
// Prinsip desain:
//   1. Assert asinkron, deassert sinkron: reset langsung aktif tanpa menunggu
//      clock, tetapi dilepas tepat pada tepi clock agar semua register keluar
//      dari reset pada siklus yang sama (tanpa metastabilitas).
//   2. Reset ditahan selama PLL belum terkunci. Kalau PLL kehilangan kunci
//      (misalnya clock masukan diganggu), seluruh chip otomatis direset:
//      fail-safe.
//   3. Reset diperpanjang minimal HOLD_CYCLES siklus. Pulsa reset sependek
//      apa pun tetap menghasilkan reset penuh, dan blok seperti zeroize
//      dijamin melihat beberapa tepi clock selama reset aktif.
//
// Antarmuka:
//   clk_50     : clock 50 MHz dari osilator papan
//   rst_n      : tombol reset, aktif rendah (asinkron)
//   clk_pll    : clock 50 MHz bersih dari PLL
//   rst_sync_n : reset global aktif rendah, tersinkron ke clk_pll
//   pll_locked : status kunci PLL (untuk LED/debug)
//
// Catatan PLL:
//   Modul ini memanggil "pll_sys". Di Quartus, pll_sys dibuat lewat
//   IP Catalog (PLL Intel FPGA IP). Di ModelSim, pakai model pll_sys_sim.v.
//   JANGAN memasukkan pll_sys_sim.v ke proyek Quartus.
//
// Catatan domain clock:
//   rst_sync_n tersinkron ke clk_pll. clk_sys berasal dari clk_pll (lewat
//   glitch_inj) dengan frekuensi dan fase yang sama, jadi aman dipakai di
//   domain clk_sys. Di chip final clk_sys = clk_pll.
// =============================================================================

module clk_rst #(
    parameter integer HOLD_CYCLES = 16   // panjang minimum reset setelah sinkron
)(
    input  wire clk_50,
    input  wire rst_n,
    output wire clk_pll,
    output wire rst_sync_n,
    output wire pll_locked
);

    // -------------------------------------------------------------------------
    // 1. PLL: 50 MHz -> 50 MHz bersih, dengan sinyal locked
    // -------------------------------------------------------------------------
    pll_sys u_pll (
        .refclk   (clk_50),
        .rst      (~rst_n),      // reset PLL aktif tinggi
        .outclk_0 (clk_pll),
        .locked   (pll_locked)
    );

    // -------------------------------------------------------------------------
    // 2. Sumber reset asinkron: aktif jika tombol ditekan ATAU PLL belum kunci
    // -------------------------------------------------------------------------
    wire arst_n = rst_n & pll_locked;

    // -------------------------------------------------------------------------
    // 3. Sinkronizer 3 tahap: assert asinkron, deassert sinkron
    //    Nilai awal 0 = chip dalam keadaan reset saat FPGA baru dikonfigurasi.
    // -------------------------------------------------------------------------
    reg [2:0] sync_ff = 3'b000;

    always @(posedge clk_pll or negedge arst_n) begin
        if (!arst_n)
            sync_ff <= 3'b000;
        else
            sync_ff <= {sync_ff[1:0], 1'b1};
    end

    wire sync_ok = sync_ff[2];

    // -------------------------------------------------------------------------
    // 4. Penahan reset: lepas reset hanya setelah HOLD_CYCLES siklus stabil
    // -------------------------------------------------------------------------
    localparam integer CW = $clog2(HOLD_CYCLES + 1);

    reg [CW-1:0] hold_cnt  = {CW{1'b0}};
    reg          rst_out_n = 1'b0;

    always @(posedge clk_pll or negedge arst_n) begin
        if (!arst_n) begin
            hold_cnt  <= {CW{1'b0}};
            rst_out_n <= 1'b0;
        end else if (!sync_ok) begin
            hold_cnt  <= {CW{1'b0}};
            rst_out_n <= 1'b0;
        end else if (hold_cnt < HOLD_CYCLES) begin
            hold_cnt  <= hold_cnt + 1'b1;
            rst_out_n <= 1'b0;
        end else begin
            rst_out_n <= 1'b1;
        end
    end

    assign rst_sync_n = rst_out_n;

endmodule

SIM/tb_clk_rst.v
// =============================================================================
// Testbench self-checking untuk modul clk_rst
// Kompilasi bersama model PLL simulasi:
//   iverilog -o tb pll_sys_sim.v clk_rst.v tb_clk_rst.v && vvp tb
// =============================================================================
`timescale 1ns/1ps

module tb_clk_rst;

    localparam integer HOLD     = 16;
    localparam integer MIN_RST  = HOLD + 3;   // sinkronizer 3 FF + penahan

    reg  clk_50 = 1'b0;
    reg  rst_n  = 1'b0;          // tombol ditekan saat menyala
    wire clk_pll;
    wire rst_sync_n;
    wire pll_locked;

    integer errors = 0;
    integer n_cyc;
    real    t1, t2;
    reg     watch_stable = 1'b0;
    integer spurious     = 0;

    clk_rst #(.HOLD_CYCLES(HOLD)) dut (
        .clk_50     (clk_50),
        .rst_n      (rst_n),
        .clk_pll    (clk_pll),
        .rst_sync_n (rst_sync_n),
        .pll_locked (pll_locked)
    );

    // Clock papan 50 MHz
    always #10 clk_50 = ~clk_50;

    initial begin
        $dumpfile("tb_clk_rst.vcd");
        $dumpvars(0, tb_clk_rst);
    end

    // -------------------------------------------------------------------------
    // Monitor 1: setiap kali reset dilepas, harus tepat setelah tepi naik clock
    // -------------------------------------------------------------------------
    always @(posedge rst_sync_n) begin
        if (clk_pll !== 1'b1) begin
            $display("[GAGAL] Reset dilepas TIDAK sinkron dengan clk_pll (t=%0t)", $time);
            errors = errors + 1;
        end
    end

    // Monitor 2: selama periode stabil, reset tidak boleh aktif sendiri
    always @(negedge rst_sync_n) if (watch_stable) spurious = spurious + 1;

    // -------------------------------------------------------------------------
    task check(input ok, input [8*64-1:0] msg);
        begin
            if (ok) $display("[LULUS] %0s", msg);
            else begin
                $display("[GAGAL] %0s (t=%0t)", msg, $time);
                errors = errors + 1;
            end
        end
    endtask

    // Hitung tepi clk_pll sampai reset dilepas (dengan batas waktu)
    task count_until_release(output integer cycles);
        begin
            cycles = 0;
            while (rst_sync_n !== 1'b1 && cycles < 1000) begin
                @(posedge clk_pll); #1;
                cycles = cycles + 1;
            end
        end
    endtask

    // -------------------------------------------------------------------------
    initial begin
        // 1. Saat menyala dengan tombol reset ditekan
        #100;
        check(rst_sync_n === 1'b0, "1a. Reset aktif saat tombol ditekan");
        check(pll_locked === 1'b0, "1b. PLL belum terkunci saat direset");

        // 2. Tombol dilepas: PLL mengunci, reset masih ditahan
        rst_n = 1'b1;
        @(posedge pll_locked); #1;
        check(rst_sync_n === 1'b0, "2. Reset masih aktif tepat saat PLL baru terkunci");

        // 3. Reset dilepas setelah sinkronizer + penahan
        count_until_release(n_cyc);
        $display("        (reset dilepas setelah %0d siklus clk_pll)", n_cyc);
        check(rst_sync_n === 1'b1 && n_cyc >= MIN_RST, "3. Reset dilepas setelah minimal HOLD+3 siklus");

        // 4. Frekuensi clk_pll = 50 MHz (periode 20 ns)
        @(posedge clk_pll); t1 = $realtime;
        @(posedge clk_pll); t2 = $realtime;
        check((t2 - t1) > 19.99 && (t2 - t1) < 20.01, "4. Periode clk_pll = 20 ns (50 MHz)");

        // 5. Stabil: tidak ada reset palsu selama 200 siklus
        watch_stable = 1'b1;
        repeat (200) @(posedge clk_pll);
        watch_stable = 1'b0;
        check(spurious == 0 && rst_sync_n === 1'b1, "5. Stabil 200 siklus tanpa reset palsu");

        // 6. Assert asinkron: tombol ditekan di tengah siklus
        @(posedge clk_pll); #5;
        rst_n = 1'b0; #1;
        check(rst_sync_n === 1'b0, "6a. Reset aktif seketika tanpa menunggu clock");
        #200 rst_n = 1'b1;
        @(posedge pll_locked); #1;
        count_until_release(n_cyc);
        check(rst_sync_n === 1'b1 && n_cyc >= MIN_RST, "6b. Pulih normal setelah tombol dilepas");

        // 7. Glitch reset sangat pendek (2 ns) tetap menghasilkan reset penuh
        @(posedge clk_pll); #3;
        rst_n = 1'b0; #2 rst_n = 1'b1; #1;
        check(rst_sync_n === 1'b0, "7a. Glitch 2 ns tetap memicu reset");
        @(posedge pll_locked); #1;
        count_until_release(n_cyc);
        check(rst_sync_n === 1'b1 && n_cyc >= MIN_RST, "7b. Glitch diperpanjang menjadi reset penuh");

        // 8. PLL kehilangan kunci (misalnya clock masukan diganggu)
        @(posedge clk_pll); #4;
        force dut.u_pll.locked = 1'b0; #1;
        check(rst_sync_n === 1'b0, "8a. Kehilangan kunci PLL langsung memicu reset");
        #100 release dut.u_pll.locked;
        @(posedge pll_locked); #1;
        count_until_release(n_cyc);
        check(rst_sync_n === 1'b1 && n_cyc >= MIN_RST, "8b. Reset dilepas lagi setelah PLL terkunci");

        // Ringkasan
        #100;
        if (errors == 0) $display("\n=== SEMUA TES LULUS ===");
        else             $display("\n=== %0d TES GAGAL ===", errors);
        $finish;
    end

endmodule

SIM/tb_clk_rst.vcd
$date
	Sat Oct 03 14:42:49 2026
$end
$version
	ModelSim Version 2020.1
$end
$timescale
	1ps
$end

$scope module tb_clk_rst $end
$var parameter 32 ! HOLD $end
$var parameter 32 " MIN_RST $end
$var reg 1 # clk_50 $end
$var reg 1 $ rst_n $end
$var wire 1 % clk_pll $end
$var wire 1 & rst_sync_n $end
$var wire 1 ' pll_locked $end
$var integer 32 ( errors $end
$var integer 32 ) n_cyc $end
$var real 64 * t1 $end
$var real 64 + t2 $end
$var reg 1 , watch_stable $end
$var integer 32 - spurious $end

$scope task check $end
$var reg 1 . ok $end
$var reg 512 / msg [511:0] $end
$upscope $end

$scope task count_until_release $end
$var integer 32 0 cycles $end
$upscope $end

$scope module dut $end
$var parameter 32 1 HOLD_CYCLES $end
$var parameter 32 2 CW $end
$var wire 1 3 clk_50 $end
$var wire 1 4 rst_n $end
$var wire 1 % clk_pll $end
$var wire 1 & rst_sync_n $end
$var wire 1 ' pll_locked $end
$var wire 1 5 arst_n $end
$var reg 3 6 sync_ff [2:0] $end
$var wire 1 7 sync_ok $end
$var reg 5 8 hold_cnt [4:0] $end
$var reg 1 9 rst_out_n $end

$scope module u_pll $end
$var parameter 32 : LOCK_CYCLES $end
$var wire 1 3 refclk $end
$var wire 1 ; rst $end
$var wire 1 % outclk_0 $end
$var reg 1 < locked $end
$var integer 32 = cnt $end
$upscope $end
$upscope $end
$upscope $end
$enddefinitions $end
#0
$dumpvars
0#
0$
0,
0<
b0 6
b0 8
09
x.
bx /
b10000 !
b10011 "
b10000 1
b101 2
b10100 :
b0 (
bx )
b0 -
b0 =
bx 0
r0 *
r0 +
0%
0&
0'
05
07
04
03
1;
$end
#10000
1#
13
#20000
0#
03
#30000
1#
13
#40000
0#
03
#50000
1#
13
#60000
0#
03
#70000
1#
13
#80000
0#
03
#90000
1#
13
#100000
1.
b11000101100001001011100010000001010010011001010111001101100101011101000010000001100001011010110111010001101001011001100010000001110011011000010110000101110100001000000111010001101111011011010110001001101111011011000010000001100100011010010111010001100101011010110110000101101110 /
b11000101100010001011100010000001010000010011000100110000100000011000100110010101101100011101010110110100100000011101000110010101110010011010110111010101101110011000110110100100100000011100110110000101100001011101000010000001100100011010010111001001100101011100110110010101110100 /
1$
0#
14
03
0;
b1 =
#110000
1#
13
#120000
0#
03
b10 =
#130000
1#
13
#140000
0#
03
b11 =
#150000
1#
13
#160000
0#
03
b100 =
#170000
1#
13
#180000
0#
03
b101 =
#190000
1#
13
#200000
0#
03
b110 =
#210000
1#
13
#220000
0#
03
b111 =
#230000
1#
13
#240000
0#
03
b1000 =
#250000
1#
13
#260000
0#
03
b1001 =
#270000
1#
13
#280000
0#
03
b1010 =
#290000
1#
13
#300000
0#
03
b1011 =
#310000
1#
13
#320000
0#
03
b1100 =
#330000
1#
13
#340000
0#
03
b1101 =
#350000
1#
13
#360000
0#
03
b1110 =
#370000
1#
13
#380000
0#
03
b1111 =
#390000
1#
13
#400000
0#
03
b10000 =
#410000
1#
13
#420000
0#
03
b10001 =
#430000
1#
13
#440000
0#
03
b10010 =
#450000
1#
13
#460000
0#
03
b10011 =
#470000
1#
13
#480000
0#
03
b10100 =
#490000
1#
13
#500000
0#
03
1<
1'
15
#501000
b110010001011100010000001010010011001010111001101100101011101000010000001101101011000010111001101101001011010000010000001100001011010110111010001101001011001100010000001110100011001010111000001100001011101000010000001110011011000010110000101110100001000000101000001001100010011000010000001100010011000010111001001110101001000000111010001100101011100100110101101110101011011100110001101101001 /
b0 0
#510000
1#
13
1%
b1 6
#511000
b1 0
#520000
0#
03
0%
#530000
1#
13
1%
b11 6
#531000
b10 0
#540000
0#
03
0%
#550000
1#
13
1%
b111 6
17
#551000
b11 0
#560000
0#
03
0%
#570000
1#
13
1%
b1 8
#571000
b100 0
#580000
0#
03
0%
#590000
1#
13
1%
b10 8
#591000
b101 0
#600000
0#
03
0%
#610000
1#
13
1%
b11 8
#611000
b110 0
#620000
0#
03
0%
#630000
1#
13
1%
b100 8
#631000
b111 0
#640000
0#
03
0%
#650000
1#
13
1%
b101 8
#651000
b1000 0
#660000
0#
03
0%
#670000
1#
13
1%
b110 8
#671000
b1001 0
#680000
0#
03
0%
#690000
1#
13
1%
b111 8
#691000
b1010 0
#700000
0#
03
0%
#710000
1#
13
1%
b1000 8
#711000
b1011 0
#720000
0#
03
0%
#730000
1#
13
1%
b1001 8
#731000
b1100 0
#740000
0#
03
0%
#750000
1#
13
1%
b1010 8
#751000
b1101 0
#760000
0#
03
0%
#770000
1#
13
1%
b1011 8
#771000
b1110 0
#780000
0#
03
0%
#790000
1#
13
1%
b1100 8
#791000
b1111 0
#800000
0#
03
0%
#810000
1#
13
1%
b1101 8
#811000
b10000 0
#820000
0#
03
0%
#830000
1#
13
1%
b1110 8
#831000
b10001 0
#840000
0#
03
0%
#850000
1#
13
1%
b1111 8
#851000
b10010 0
#860000
0#
03
0%
#870000
1#
13
1%
b10000 8
#871000
b10011 0
#880000
0#
03
0%
#890000
1#
13
1%
19
1&
#891000
b10100 0
b10100 )
b110011001011100010000001010010011001010111001101100101011101000010000001100100011010010110110001100101011100000110000101110011001000000111001101100101011101000110010101101100011000010110100000100000011011010110100101101110011010010110110101100001011011000010000001001000010011110100110001000100001010110011001100100000011100110110100101101011011011000111010101110011 /
#900000
0#
03
0%
#910000
1#
13
1%
r910 *
#920000
0#
03
0%
#930000
1#
13
1%
r930 +
b11010000101110001000000101000001100101011100100110100101101111011001000110010100100000011000110110110001101011010111110111000001101100011011000010000000111101001000000011001000110000001000000110111001110011001000000010100000110101001100000010000001001101010010000111101000101001 /
1,
